README.rst
setup.py
stockfishpy/__init__.py
stockfishpy/stockfishpy.py
stockfishpy.egg-info/PKG-INFO
stockfishpy.egg-info/SOURCES.txt
stockfishpy.egg-info/dependency_links.txt
stockfishpy.egg-info/not-zip-safe
stockfishpy.egg-info/top_level.txt