Metadata-Version: 1.1
Name: stockfishpy
Version: 1.0.2
Summary: Simple python Stockfish wrapper
Home-page: https://github.com/Dani4kor/stockfishpy
Author: dani4kor
Author-email: dani4kor@gmail.com
License: GPLv3
Platform: UNKNOWN
Classifier: Programming Language :: Python
Classifier: Development Status :: 5 - Production/Stable
Classifier: Intended Audience :: Developers
Classifier: License :: OSI Approved :: GNU General Public License (GPL)
Classifier: Topic :: Software Development :: Libraries :: Python Modules
